pycout/__init__.py
pycout/cout.py
pycout-1.0.2.dist-info/LICENSE
pycout-1.0.2.dist-info/METADATA
pycout-1.0.2.dist-info/WHEEL
pycout-1.0.2.dist-info/top_level.txt
pycout-1.0.2.dist-info/RECORD
