Metadata-Version: 2.1
Name: pycout
Version: 1.0.2
Summary: C++'s cout for Python 
Home-page: http://github.com/ebonnal/pycout
Author: Enzo Bonnal
Author-email: bonnal.enzo.dev@gmail.com
License: Apache 2.
License-File: LICENSE
